player/__init__.py
player/config.py
player/main.py
player/py.typed
player/gui/__init__.py
player/gui/gui.tcss
player/gui/player.py
player/gui/player_service.py
player/utils/__init__.py
player/utils/download.py
player/utils/ffmpeg.py
player/utils/file_operations.py
player/utils/url_helpers.py
musicly-0.1.9.dist-info/METADATA
musicly-0.1.9.dist-info/WHEEL
musicly-0.1.9.dist-info/entry_points.txt
musicly-0.1.9.dist-info/top_level.txt
musicly-0.1.9.dist-info/RECORD
